{
  "version": "6",
  "dialect": "sqlite",
  "id": "c55b034a-a89a-401f-8fe4-9e0eebfe9f7c",
  "prevId": "bb537c98-dda9-4c81-b6dd-c909c96ad3cf",
  "tables": {
    "recipes": {
      "name": "recipes",
      "columns": {
        "id": {
          "name": "id",
          "type": "integer",
          "primaryKey": true,
          "notNull": true,
          "autoincrement": true
        },
        "transformed_cover_image": {
          "name": "transformed_cover_image",
          "type": "text",
          "primaryKey": false,
          "notNull": false,
          "autoincrement": false
        },
        "angle": {
          "name": "angle",
          "type": "text",
          "primaryKey": false,
          "notNull": false,
          "autoincrement": false
        },
        "cover_image": {
          "name": "cover_image",
          "type": "text",
          "primaryKey": false,
          "notNull": false,
          "autoincrement": false
        },
        "title": {
          "name": "title",
          "type": "text",
          "primaryKey": false,
          "notNull": true,
          "autoincrement": false
        },
        "slug": {
          "name": "slug",
          "type": "text",
          "primaryKey": false,
          "notNull": true,
          "autoincrement": false
        },
        "description": {
          "name": "description",
          "type": "text",
          "primaryKey": false,
          "notNull": false,
          "autoincrement": false
        },
        "category": {
          "name": "category",
          "type": "text",
          "primaryKey": false,
          "notNull": false,
          "autoincrement": false,
          "default": "'General'"
        },
        "prep_time": {
          "name": "prep_time",
          "type": "text",
          "primaryKey": false,
          "notNull": false,
          "autoincrement": false
        },
        "cook_time": {
          "name": "cook_time",
          "type": "text",
          "primaryKey": false,
          "notNull": false,
          "autoincrement": false
        },
        "total_time": {
          "name": "total_time",
          "type": "text",
          "primaryKey": false,
          "notNull": false,
          "autoincrement": false
        },
        "servings": {
          "name": "servings",
          "type": "integer",
          "primaryKey": false,
          "notNull": false,
          "autoincrement": false
        },
        "s3_key": {
          "name": "s3_key",
          "type": "text",
          "primaryKey": false,
          "notNull": true,
          "autoincrement": false
        },
        "old_title": {
          "name": "old_title",
          "type": "text",
          "primaryKey": false,
          "notNull": false,
          "autoincrement": false
        },
        "scraped_url": {
          "name": "scraped_url",
          "type": "text",
          "primaryKey": false,
          "notNull": false,
          "autoincrement": false
        },
        "created_at": {
          "name": "created_at",
          "type": "text",
          "primaryKey": false,
          "notNull": false,
          "autoincrement": false,
          "default": "CURRENT_TIMESTAMP"
        }
      },
      "indexes": {
        "recipes_slug_unique": {
          "name": "recipes_slug_unique",
          "columns": [
            "slug"
          ],
          "isUnique": true
        }
      },
      "foreignKeys": {},
      "compositePrimaryKeys": {},
      "uniqueConstraints": {},
      "checkConstraints": {}
    }
  },
  "views": {},
  "enums": {},
  "_meta": {
    "schemas": {},
    "tables": {},
    "columns": {}
  },
  "internal": {
    "indexes": {}
  }
}